lagertha/__init__.py
lagertha/cli.py
lagertha/lagertha.py
lagertha-0.1.0.dist-info/AUTHORS.rst
lagertha-0.1.0.dist-info/METADATA
lagertha-0.1.0.dist-info/WHEEL
lagertha-0.1.0.dist-info/entry_points.txt
lagertha-0.1.0.dist-info/top_level.txt
lagertha-0.1.0.dist-info/RECORD
