Metadata-Version: 2.1
Name: lagertha
Version: 0.1.0
Summary: An application that allows task scheduling
Home-page: https://github.com/juanmcristobal/lagertha
Author: Juan Manuel Cristóbal Moreno
Author-email: juanmcristobal@gmail.com
License: UNKNOWN
Keywords: lagertha
Platform: UNKNOWN
Classifier: Development Status :: 2 - Pre-Alpha
Classifier: Intended Audience :: Developers
Classifier: Natural Language :: English
Classifier: Programming Language :: Python :: 2
Classifier: Programming Language :: Python :: 2.7
Classifier: Programming Language :: Python :: 3
Classifier: Programming Language :: Python :: 3.4
Classifier: Programming Language :: Python :: 3.5
Classifier: Programming Language :: Python :: 3.6
Classifier: Programming Language :: Python :: 3.7
Requires-Dist: Click (>=6.0)
